brainunit/brainunit/__init__.py
brainunit/brainunit/_base.py
brainunit/brainunit/_celsius.py
brainunit/brainunit/_unit_common.py
brainunit/brainunit/_unit_constants.py
brainunit/brainunit/_unit_shortcuts.py
brainunit/brainunit/constants.py
brainunit/brainunit/autograd/__init__.py
brainunit/brainunit/autograd/_hessian.py
brainunit/brainunit/autograd/_jacobian.py
brainunit/brainunit/autograd/_value_and_grad.py
brainunit/brainunit/autograd/_vector_grad.py
brainunit/brainunit/fft/__init__.py
brainunit/brainunit/fft/_fft_change_unit.py
brainunit/brainunit/fft/_fft_keep_unit.py
brainunit/brainunit/lax/__init__.py
brainunit/brainunit/lax/_lax_accept_unitless.py
brainunit/brainunit/lax/_lax_array_creation.py
brainunit/brainunit/lax/_lax_change_unit.py
brainunit/brainunit/lax/_lax_keep_unit.py
brainunit/brainunit/lax/_lax_linalg.py
brainunit/brainunit/lax/_lax_remove_unit.py
brainunit/brainunit/lax/_misc.py
brainunit/brainunit/linalg/__init__.py
brainunit/brainunit/linalg/_linalg_change_unit.py
brainunit/brainunit/linalg/_linalg_keep_unit.py
brainunit/brainunit/linalg/_linalg_remove_unit.py
brainunit/brainunit/math/__init__.py
brainunit/brainunit/math/_activation.py
brainunit/brainunit/math/_alias.py
brainunit/brainunit/math/_einops.py
brainunit/brainunit/math/_fun_accept_unitless.py
brainunit/brainunit/math/_fun_array_creation.py
brainunit/brainunit/math/_fun_change_unit.py
brainunit/brainunit/math/_fun_keep_unit.py
brainunit/brainunit/math/_fun_remove_unit.py
brainunit/brainunit/math/_misc.py
brainunit/brainunit/math/fft.py
brainunit/brainunit/math/linalg.py
brainunit/brainunit/sparse/__init__.py
brainunit/brainunit/sparse/_block_csr.py
brainunit/brainunit/sparse/_block_ell.py
brainunit/brainunit/sparse/_coo.py
brainunit/brainunit/sparse/_csr.py
saiunit/__init__.py
saiunit/_base.py
saiunit/_base_test.py
saiunit/_celsius.py
saiunit/_celsius_test.py
saiunit/_compatible_import.py
saiunit/_matplotlib_compat.py
saiunit/_matplotlib_compat_test.py
saiunit/_misc.py
saiunit-0.1.4.dist-info/licenses/LICENSE
saiunit-0.1.4.dist-info/METADATA
saiunit-0.1.4.dist-info/WHEEL
saiunit-0.1.4.dist-info/top_level.txt
saiunit-0.1.4.dist-info/RECORD
