Metadata-Version: 2.4
Name: saiunit
Version: 0.1.4
Summary: Enabling Unit-aware Computations for AI-driven Scientific Computing.
Author-email: SAIUnit Developers <chao.brain@qq.com>
License-Expression: Apache-2.0
Project-URL: homepage, https://github.com/chaobrain/saiunit
Project-URL: repository, https://github.com/chaobrain/saiunit
Project-URL: Bug Tracker, https://github.com/chaobrain/saiunit/issues
Project-URL: Documentation, https://saiunit.readthedocs.io/
Keywords: physical unit,physical quantity,brain modeling,scientific computing,AI for science
Classifier: Natural Language :: English
Classifier: Operating System :: OS Independent
Classifier: Development Status :: 4 - Beta
Classifier: Intended Audience :: Developers
Classifier: Intended Audience :: Science/Research
Classifier: Programming Language :: Python
Classifier: Programming Language :: Python :: 3
Classifier: Programming Language :: Python :: 3.10
Classifier: Programming Language :: Python :: 3.11
Classifier: Programming Language :: Python :: 3.12
Classifier: Programming Language :: Python :: 3.13
Classifier: Programming Language :: Python :: 3.14
Classifier: Topic :: Scientific/Engineering :: Bio-Informatics
Classifier: Topic :: Scientific/Engineering :: Mathematics
Classifier: Topic :: Scientific/Engineering :: Artificial Intelligence
Classifier: Topic :: Software Development :: Libraries
Requires-Python: >=3.10
License-File: LICENSE
Requires-Dist: jax
Requires-Dist: numpy
Requires-Dist: typing_extensions
Provides-Extra: testing
Requires-Dist: pytest; extra == "testing"
Provides-Extra: cpu
Requires-Dist: jax[cpu]; extra == "cpu"
Provides-Extra: cuda12
Requires-Dist: jax[cuda12]; extra == "cuda12"
Provides-Extra: cuda13
Requires-Dist: jax[cuda13]; extra == "cuda13"
Provides-Extra: tpu
Requires-Dist: jax[tpu]; extra == "tpu"
Dynamic: license-file
